MANIFEST.in
README.rst
setup.py
collective/__init__.py
collective.tablepage.egg-info/PKG-INFO
collective.tablepage.egg-info/SOURCES.txt
collective.tablepage.egg-info/dependency_links.txt
collective.tablepage.egg-info/entry_points.txt
collective.tablepage.egg-info/namespace_packages.txt
collective.tablepage.egg-info/not-zip-safe
collective.tablepage.egg-info/requires.txt
collective.tablepage.egg-info/top_level.txt
collective/tablepage/__init__.py
collective/tablepage/catalog.py
collective/tablepage/config.py
collective/tablepage/configure.zcml
collective/tablepage/events.py
collective/tablepage/interfaces.py
collective/tablepage/permissions.zcml
collective/tablepage/profiles.zcml
collective/tablepage/runI18ndude.sh
collective/tablepage/setuphandlers.py
collective/tablepage/testing.py
collective/tablepage/vocabularies.py
collective/tablepage/vocabularies.zcml
collective/tablepage/Extensions/install.py
collective/tablepage/browser/__init__.py
collective/tablepage/browser/configure.zcml
collective/tablepage/browser/label.py
collective/tablepage/browser/multiple_tables.py
collective/tablepage/browser/table.py
collective/tablepage/browser/updownload.py
collective/tablepage/browser/view.py
collective/tablepage/browser/images/add.png
collective/tablepage/browser/images/document_icon.gif
collective/tablepage/browser/images/download_data.png
collective/tablepage/browser/images/edit.png
collective/tablepage/browser/images/fullscreencollapse_icon.png
collective/tablepage/browser/images/fullscreenexpand_icon.png
collective/tablepage/browser/images/labeling.png
collective/tablepage/browser/images/move.png
collective/tablepage/browser/images/move_down.png
collective/tablepage/browser/images/move_up.png
collective/tablepage/browser/images/refresh.png
collective/tablepage/browser/images/remove.png
collective/tablepage/browser/images/upload_data.png
collective/tablepage/browser/resources/edit-record.js
collective/tablepage/browser/resources/edit-table.js
collective/tablepage/browser/resources/jquery.dataTables.rowGrouping.js
collective/tablepage/browser/resources/jquery.dataTables.rowGrouping.min.js
collective/tablepage/browser/resources/tablepage.js
collective/tablepage/browser/resources/tablepage_edit.css
collective/tablepage/browser/resources/tablepage_search.css
collective/tablepage/browser/templates/edit-label.pt
